impurity/__init__.py
impurity-0.1.dist-info/LICENSE
impurity-0.1.dist-info/METADATA
impurity-0.1.dist-info/WHEEL
impurity-0.1.dist-info/top_level.txt
impurity-0.1.dist-info/RECORD
