Metadata-Version: 2.1
Name: impurity
Version: 0.1
Summary: Clean any data type based on requiement.
Author-email: Soumyo Deep Gupta <deep.main.ac@gmail.com>
Maintainer-email: Soumyo Deep Gupta <deep.main.ac@gmail.com>
License: MIT License
Project-URL: GitHub, https://github.com/d33p0st/impurity
Project-URL: Issues, https://github.com/d33p0st/impurity/issues
Project-URL: Pull Requests, https://github.com/d33p0st/impurity/pulls
Keywords: d33p0st,impurity,sanitizer,string,sanitiser
Classifier: Development Status :: 4 - Beta
Classifier: Topic :: Software Development :: Libraries :: Python Modules
Classifier: Programming Language :: Python :: 3.10
Classifier: Programming Language :: Python :: 3.11
Classifier: Programming Language :: Python :: 3.12
Classifier: License :: OSI Approved :: MIT License
Classifier: Operating System :: OS Independent
Requires-Python: >=3.10
License-File: LICENSE
Requires-Dist: pytest
Requires-Dist: pytest-cov
